[{"entities":{"urls":[{"start":155,"end":178,"url":"https://t.co/FwFhuiKGMt","expanded_url":"https://twitter.com/RBICP/status/1426485684668407815/photo/1","display_url":"pic.twitter.com/FwFhuiKGMt"}],"annotations":[{"start":15,"end":27,"probability":0.8687,"type":"Place","normalized_text":"Parsloes Park"},{"start":91,"end":101,"probability":0.3729,"type":"Person","normalized_text":"Gores Brook"}],"mentions":[{"start":104,"end":118,"username":"BDParkRangers","id":"1088435907051618304"},{"start":119,"end":130,"username":"WildLondon","id":"20505346"},{"start":131,"end":140,"username":"Thames21","id":"31800858"},{"start":141,"end":154,"username":"Summeroffest","id":"743867469392134144"}],"hashtags":{}},"text":"Come see us at Parsloes Park today where we'll be talking about the park's lost river- the Gores Brook! @BDParkRangers @WildLondon @Thames21 @Summeroffest https://t.co/FwFhuiKGMt","conversation_id":"1426485684668407815","lang":"en","created_at":"2021-08-14T10:07:44.000Z","public_metrics":{"retweet_count":1,"reply_count":0,"like_count":7,"quote_count":1},"possibly_sensitive":false,"author_id":"1402641912448831497","source":"Twitter for Android","geo":{"place_id":"07d9e6c6bfc87000"},"attachments":{"media_keys":["3_1426485678381076485"]},"id":"1426485684668407815","referenced_tweets":{}},{"entities":{"urls":{},"annotations":[{"start":37,"end":47,"probability":0.7839,"type":"Person","normalized_text":"Mayes Brook"},{"start":57,"end":62,"probability":0.659,"type":"Place","normalized_text":"Thames"},{"start":76,"end":86,"probability":0.8023,"type":"Person","normalized_text":"Gores Brook"}],"mentions":{},"hashtags":{}},"text":"Lovely walk with husband &amp; son along Mayes Brook, to the Thames, back along Gores Brook.","conversation_id":"1339633401431814144","lang":"en","created_at":"2020-12-17T18:07:46.000Z","public_metrics":{"retweet_count":0,"reply_count":0,"like_count":0,"quote_count":0},"possibly_sensitive":false,"author_id":"113385823","source":"Twitter Web App","geo":{},"attachments":{"media_keys":{}},"id":"1339633401431814144","referenced_tweets":{}},{"entities":{"urls":[{"start":250,"end":273,"url":"https://t.co/z7dkeroVK2","expanded_url":"https://diamondgeezer.blogspot.com/2015/05/mayes-brook.html","display_url":"diamondgeezer.blogspot.com/2015/05/mayes-…","status":200,"unwound_url":"https://diamondgeezer.blogspot.com/2015/05/mayes-brook.html"}],"annotations":[{"start":45,"end":55,"probability":0.5356,"type":"Person","normalized_text":"Mayes Brook"},{"start":233,"end":243,"probability":0.8448,"type":"Person","normalized_text":"Gores Brook"}],"mentions":[{"start":14,"end":28,"username":"diamondgeezer","id":"54943"},{"start":65,"end":80,"username":"diamondgzrblog","id":"804403268445212672"}],"hashtags":{}},"text":"Back in 2015, @diamondgeezer walked down the Mayes Brook. In his @diamondgzrblog he said that he thought he could guarantee that nobody would follow his route.  Well he was wrong - today we did just that &amp; came back by following the Gores Brook.\nhttps://t.co/z7dkeroVK2","conversation_id":"1339627658066317312","lang":"en","created_at":"2020-12-17T17:44:57.000Z","public_metrics":{"retweet_count":0,"reply_count":0,"like_count":0,"quote_count":0},"possibly_sensitive":false,"author_id":"78710815","source":"Twitter Web App","geo":{},"attachments":{"media_keys":{}},"id":"1339627658066317312","referenced_tweets":{}},{"entities":{"urls":[{"start":237,"end":260,"url":"https://t.co/O2nhx9tKsY","expanded_url":"https://twitter.com/TheGreenMonk1/status/1336007066406838278/photo/1","display_url":"pic.twitter.com/O2nhx9tKsY"}],"annotations":[{"start":52,"end":55,"probability":0.3814,"type":"Organization","normalized_text":"TPLF"},{"start":218,"end":225,"probability":0.8301,"type":"Person","normalized_text":"Al Gores"}],"mentions":[{"start":0,"end":14,"username":"furtuna_Desta","id":"2947126711"},{"start":15,"end":26,"username":"brook_lema","id":"768694144206249985"},{"start":27,"end":40,"username":"AbiyAhmedAli","id":"1168167671151628290"}],"hashtags":{}},"text":"@furtuna_Desta @brook_lema @AbiyAhmedAli I mean the TPLF spokesperson publicly and proudly admitted TPLF started the conflict with the excuse of “preemptive attack.” Why are you acting like that video doesn’t exist on Al Gores internet? https://t.co/O2nhx9tKsY","conversation_id":"1335538238212222976","lang":"en","created_at":"2020-12-07T17:58:01.000Z","public_metrics":{"retweet_count":0,"reply_count":0,"like_count":0,"quote_count":0},"possibly_sensitive":false,"author_id":"1255090260515737603","source":"Twitter for iPhone","geo":{},"attachments":{"media_keys":["16_1336007061084246017"]},"id":"1336007066406838278","in_reply_to_user_id":"2947126711","referenced_tweets":[{"type":"replied_to","id":"1335769621022982144"}]},{"entities":{"urls":{},"annotations":[{"start":55,"end":72,"probability":0.6279,"type":"Place","normalized_text":"Gores brook School"}],"mentions":[{"start":171,"end":184,"username":"GoresbrookSc","id":"3557102295"}],"hashtags":{}},"text":"Next week we will be celebrating Anti-Bullying week at Gores brook School. Please help support this by talking with your children about ways we can be nice to each other. @GoresbrookSc","conversation_id":"1327261718322569218","lang":"en","created_at":"2020-11-13T14:47:07.000Z","public_metrics":{"retweet_count":2,"reply_count":0,"like_count":9,"quote_count":0},"possibly_sensitive":false,"author_id":"1282967814207426561","source":"Twitter Web App","geo":{},"attachments":{"media_keys":{}},"id":"1327261718322569218","referenced_tweets":{}},{"entities":{"urls":{},"annotations":[{"start":166,"end":176,"probability":0.2867,"type":"Place","normalized_text":"Gores Brook"}],"mentions":[{"start":0,"end":13,"username":"cornish_jack","id":"107095378"},{"start":14,"end":30,"username":"Ramblers_London","id":"3503639416"},{"start":31,"end":44,"username":"ThamesPathNT","id":"4901445233"},{"start":45,"end":61,"username":"walkngclasshero","id":"358228655"},{"start":62,"end":75,"username":"CRTSouthEast","id":"93601662"},{"start":76,"end":91,"username":"CapitalWalkers","id":"2276289708"},{"start":92,"end":102,"username":"LondonNPC","id":"2241347358"},{"start":103,"end":119,"username":"museumofwalking","id":"446517029"},{"start":120,"end":135,"username":"summerstown182","id":"2319484106"},{"start":136,"end":150,"username":"TheStreetTree","id":"3608836816"},{"start":151,"end":161,"username":"gojauntly","id":"737953770043232256"}],"hashtags":{}},"text":"@cornish_jack @Ramblers_London @ThamesPathNT @walkngclasshero @CRTSouthEast @CapitalWalkers @LondonNPC @museumofwalking @summerstown182 @TheStreetTree @gojauntly The Gores Brook is very important for local wildlife, and the Environment Agency sluice needs to be fenced off, but I’ve not found any record of this short right-of-way been legally closed off (2/2)","conversation_id":"1325016035536363522","lang":"en","created_at":"2020-11-08T18:42:48.000Z","public_metrics":{"retweet_count":0,"reply_count":1,"like_count":2,"quote_count":0},"possibly_sensitive":false,"author_id":"81595145","source":"Twitter Web App","geo":{},"attachments":{"media_keys":{}},"id":"1325509089598861312","in_reply_to_user_id":"81595145","referenced_tweets":[{"type":"replied_to","id":"1325508837349208064"}]},{"entities":{"urls":[{"start":398,"end":421,"url":"https://t.co/Ko5wqd9KKz","expanded_url":"https://twitter.com/iantokelove/status/1325508837349208064/photo/1","display_url":"pic.twitter.com/Ko5wqd9KKz"}],"annotations":[{"start":212,"end":215,"probability":0.5226,"type":"Person","normalized_text":"Jack"},{"start":320,"end":330,"probability":0.645,"type":"Place","normalized_text":"Gores Brook"}],"mentions":[{"start":0,"end":13,"username":"cornish_jack","id":"107095378"},{"start":14,"end":30,"username":"Ramblers_London","id":"3503639416"},{"start":31,"end":44,"username":"ThamesPathNT","id":"4901445233"},{"start":45,"end":61,"username":"walkngclasshero","id":"358228655"},{"start":62,"end":75,"username":"CRTSouthEast","id":"93601662"},{"start":76,"end":91,"username":"CapitalWalkers","id":"2276289708"},{"start":92,"end":102,"username":"LondonNPC","id":"2241347358"},{"start":103,"end":119,"username":"museumofwalking","id":"446517029"},{"start":120,"end":135,"username":"summerstown182","id":"2319484106"},{"start":136,"end":150,"username":"TheStreetTree","id":"3608836816"},{"start":151,"end":161,"username":"gojauntly","id":"737953770043232256"}],"hashtags":{}},"text":"@cornish_jack @Ramblers_London @ThamesPathNT @walkngclasshero @CRTSouthEast @CapitalWalkers @LondonNPC @museumofwalking @summerstown182 @TheStreetTree @gojauntly Interestingly, we found a blocked public footpath Jack, something which I suspect is right up your street. OS maps show a there-and-back route to the east of Gores Brook, by the industrial estate, but it’s now behind locked gates (1/2) https://t.co/Ko5wqd9KKz","conversation_id":"1325016035536363522","lang":"en","created_at":"2020-11-08T18:41:48.000Z","public_metrics":{"retweet_count":0,"reply_count":1,"like_count":1,"quote_count":0},"possibly_sensitive":false,"author_id":"81595145","source":"Twitter Web App","geo":{},"attachments":{"media_keys":["3_1325507135761952768"]},"id":"1325508837349208064","in_reply_to_user_id":"107095378","referenced_tweets":[{"type":"replied_to","id":"1325504363394117632"}]},{"entities":{"urls":[{"start":199,"end":222,"url":"https://t.co/rzN409wIKl","expanded_url":"https://twitter.com/iantokelove/status/1325405632908947456/photo/1","display_url":"pic.twitter.com/rzN409wIKl"},{"start":199,"end":222,"url":"https://t.co/rzN409wIKl","expanded_url":"https://twitter.com/iantokelove/status/1325405632908947456/photo/1","display_url":"pic.twitter.com/rzN409wIKl"},{"start":199,"end":222,"url":"https://t.co/rzN409wIKl","expanded_url":"https://twitter.com/iantokelove/status/1325405632908947456/photo/1","display_url":"pic.twitter.com/rzN409wIKl"},{"start":199,"end":222,"url":"https://t.co/rzN409wIKl","expanded_url":"https://twitter.com/iantokelove/status/1325405632908947456/photo/1","display_url":"pic.twitter.com/rzN409wIKl"}],"annotations":[{"start":37,"end":47,"probability":0.6038,"type":"Place","normalized_text":"Gores Brook"}],"mentions":{},"hashtags":[{"start":55,"end":64,"tag":"Dagenham"},{"start":154,"end":165,"tag":"slimemould"},{"start":186,"end":198,"tag":"weirdnature"}]},"text":"Walking the landfill overlooking the Gores Brook &amp; #Dagenham, these puzzling ‘fungi’ had us stumped. Turns out it's the fantastically named ‘dog sick #slimemould’ - a top example of #weirdnature https://t.co/rzN409wIKl","conversation_id":"1325405632908947456","lang":"en","created_at":"2020-11-08T11:51:42.000Z","public_metrics":{"retweet_count":2,"reply_count":1,"like_count":9,"quote_count":0},"possibly_sensitive":false,"author_id":"81595145","source":"Twitter Web App","geo":{},"attachments":{"media_keys":["3_1325403896513236992","3_1325403937239932928","3_1325403958978994176","3_1325403981963735042"]},"id":"1325405632908947456","referenced_tweets":{}},{"entities":{"urls":{},"annotations":{},"mentions":[{"start":161,"end":175,"username":"Ms_Nizami_WWA","id":"1177512707899023360"},{"start":176,"end":187,"username":"BeeharryMs","id":"1184771615638413313"},{"start":188,"end":202,"username":"Miss_Song_WWA","id":"1141609241347809280"},{"start":203,"end":219,"username":"Miss_Dubuna_WWA","id":"1172438330190905344"}],"hashtags":{}},"text":"Im very confused as she keeps tagging me and saying random stuff to me. She's saying she's from the gores brook school but i'm not very sure! She's Miss Asthma. @Ms_Nizami_WWA @BeeharryMs @Miss_Song_WWA @Miss_Dubuna_WWA","conversation_id":"1246010674515521536","lang":"en","created_at":"2020-04-03T09:44:29.000Z","public_metrics":{"retweet_count":0,"reply_count":2,"like_count":1,"quote_count":0},"possibly_sensitive":false,"author_id":"1243970001519984640","source":"Twitter Web App","geo":{},"attachments":{"media_keys":{}},"id":"1246010674515521536","referenced_tweets":{}},{"entities":{"urls":{},"annotations":{},"mentions":[{"start":0,"end":13,"username":"_williamsg96","id":"800359874018185216"}],"hashtags":{}},"text":"@_williamsg96 stands for come on you gores brook","conversation_id":"1240395121687961600","lang":"en","created_at":"2020-03-18T21:57:46.000Z","public_metrics":{"retweet_count":0,"reply_count":0,"like_count":1,"quote_count":0},"possibly_sensitive":false,"author_id":"1209814288451457025","source":"Twitter for iPhone","geo":{},"attachments":{"media_keys":{}},"id":"1240397008155955204","in_reply_to_user_id":"1209814288451457025","referenced_tweets":[{"type":"replied_to","id":"1240396868217114625"}]},{"entities":{"urls":{},"annotations":{},"mentions":[{"start":0,"end":8,"username":"KoftheP","id":"1060057345"}],"hashtags":{}},"text":"@KoftheP Derwent res loop yesterday. Winstone Lea Tor to Gut Throat Bridge bone dry. Winn Hill and then Potato Alley also in great condition. Finally Locker Brook then down Gores also surprisingly dry.","conversation_id":"1143065604372516866","lang":"en","created_at":"2019-06-24T07:57:31.000Z","public_metrics":{"retweet_count":1,"reply_count":1,"like_count":2,"quote_count":0},"possibly_sensitive":false,"author_id":"18185455","source":"Twitter Web Client","geo":{},"attachments":{"media_keys":{}},"id":"1143065604372516866","in_reply_to_user_id":"1060057345","referenced_tweets":{}},{"entities":{"urls":{},"annotations":[{"start":43,"end":47,"probability":0.9704,"type":"Person","normalized_text":"Gores"},{"start":135,"end":145,"probability":0.858,"type":"Person","normalized_text":"Brook Lopez"}],"mentions":[{"start":0,"end":9,"username":"thommc18","id":"1491110431"},{"start":10,"end":26,"username":"Paul_Brown_Bear","id":"49998468"}],"hashtags":{}},"text":"@thommc18 @Paul_Brown_Bear You sounds like Gores, “that double double guy.” He’s a number three/four option on a playoff team at best. Brook Lopez outplayed him in the MIL series.","conversation_id":"1141405423964184576","lang":"en","created_at":"2019-06-19T22:53:52.000Z","public_metrics":{"retweet_count":0,"reply_count":2,"like_count":2,"quote_count":0},"possibly_sensitive":false,"author_id":"1103149178073563137","source":"Twitter for iPhone","geo":{},"attachments":{"media_keys":{}},"id":"1141479237788078081","in_reply_to_user_id":"1491110431","referenced_tweets":[{"type":"replied_to","id":"1141454179996753920"}]},{"entities":{"urls":{},"annotations":[{"start":31,"end":41,"probability":0.9843,"type":"Person","normalized_text":"Brook Lopez"},{"start":67,"end":71,"probability":0.9954,"type":"Person","normalized_text":"Andre"},{"start":132,"end":136,"probability":0.9613,"type":"Person","normalized_text":"Gores"},{"start":156,"end":162,"probability":0.5987,"type":"Place","normalized_text":"Wichita"}],"mentions":[{"start":0,"end":10,"username":"lazchance","id":"25218618"}],"hashtags":{}},"text":"@lazchance I saw someone RT a “Brook Lopez is only making 3.5 mil, Andre is making 25” hot take last night and it just made me wish Gores moves the team to Wichita","conversation_id":"1119979071964942337","lang":"en","created_at":"2019-04-21T21:36:45.000Z","public_metrics":{"retweet_count":0,"reply_count":1,"like_count":0,"quote_count":0},"possibly_sensitive":false,"author_id":"21792067","source":"Twitter for iPhone","geo":{},"attachments":{"media_keys":{}},"id":"1120078947214090242","in_reply_to_user_id":"25218618","referenced_tweets":[{"type":"replied_to","id":"1119979071964942337"}]},{"entities":{"urls":{},"annotations":[{"start":3,"end":7,"probability":0.9565,"type":"Person","normalized_text":"Gores"},{"start":16,"end":23,"probability":0.9967,"type":"Person","normalized_text":"Drummond"},{"start":113,"end":123,"probability":0.9415,"type":"Person","normalized_text":"Brook Lopez"}],"mentions":{},"hashtags":{}},"text":"Is Gores saying Drummond is someone they can build around to increase his trade value? Dude is getting punked by Brook Lopez lolololololol","conversation_id":"1090421760510578688","lang":"en","created_at":"2019-01-30T01:29:41.000Z","public_metrics":{"retweet_count":1,"reply_count":0,"like_count":2,"quote_count":0},"possibly_sensitive":false,"author_id":"850933086921658369","source":"Twitter for iPhone","geo":{},"attachments":{"media_keys":{}},"id":"1090421760510578688","referenced_tweets":{}},{"entities":{"urls":{},"annotations":[{"start":57,"end":64,"probability":0.5016,"type":"Organization","normalized_text":"Dagenham"},{"start":97,"end":107,"probability":0.8671,"type":"Person","normalized_text":"Gores Brook"}],"mentions":[{"start":0,"end":13,"username":"weeklywhinge","id":"1834487857"},{"start":14,"end":26,"username":"seanjonesqc","id":"169137527"}],"hashtags":{}},"text":"@weeklywhinge @seanjonesqc I could write stories from my Dagenham childhood: Five wonder why the Gores Brook has turned blue with effluent.","conversation_id":"1087122416596381696","lang":"en","created_at":"2019-01-21T08:34:49.000Z","public_metrics":{"retweet_count":0,"reply_count":0,"like_count":1,"quote_count":0},"possibly_sensitive":false,"author_id":"54626188","source":"Twitter for Android","geo":{},"attachments":{"media_keys":{}},"id":"1087267257565265920","in_reply_to_user_id":"1834487857","referenced_tweets":[{"type":"replied_to","id":"1087129272635006976"}]},{"entities":{"urls":[{"start":113,"end":136,"url":"https://t.co/HANxHgtzUJ","expanded_url":"http://tipsterstreet.com","display_url":"tipsterstreet.com","status":200,"title":"Tipster Street","description":"Join 89'000+ members receiving free tips every day Neil 'the founder' had worked in the racing industry as a tipster for twenty years and had become increasingly fed up with the amount of scam and expensive services on the market. Indeed in his earlier years as a gambler Neil himself had fallen for fowl of scam products Understanding the need for a professional and transparent platform where tipsters could be viewed with full detailed results within one web site, The Tipster Street platform was born and","unwound_url":"https://www.tipsterstreet.com/"},{"start":137,"end":160,"url":"https://t.co/iz4kmkBp2g","expanded_url":"https://twitter.com/tipsterstreet/status/964159891270258694/photo/1","display_url":"pic.twitter.com/iz4kmkBp2g"}],"annotations":{},"mentions":{},"hashtags":[{"start":100,"end":112,"tag":"HorseRacing"}]},"text":"Fontwell 15:10\n\n1st Bramble Brook 9/5\n2nd Rothman 8/11F\n3rd Gores Island 13/2\n\n3 Ran\nGoing:  Heavy\n\n#HorseRacing\nhttps://t.co/HANxHgtzUJ https://t.co/iz4kmkBp2g","conversation_id":"964159891270258694","lang":"en","created_at":"2018-02-15T15:30:05.000Z","public_metrics":{"retweet_count":0,"reply_count":0,"like_count":0,"quote_count":0},"possibly_sensitive":false,"author_id":"145003514","source":"Tipster Street","geo":{},"attachments":{"media_keys":["3_964159887893778432"]},"id":"964159891270258694","referenced_tweets":{}},{"entities":{"urls":[{"start":106,"end":129,"url":"https://t.co/kR9ivncNMI","expanded_url":"http://www.racinguk.com/results/161271-happy-birthday-kate-digweed-love-gordon-racing-handicap-chase-4","display_url":"racinguk.com/results/161271…"}],"annotations":[{"start":9,"end":21,"probability":0.8297,"type":"Place","normalized_text":"Fontwell Park"}],"mentions":{},"hashtags":{}},"text":"15:10 at Fontwell Park\n\n1. Bramble Brook 9/5\n2. Rothman 8/11 f\n3. Gores Island 13/2\n\nFull results here ▶️ https://t.co/kR9ivncNMI","conversation_id":"964156458437931008","lang":"en","created_at":"2018-02-15T15:16:27.000Z","public_metrics":{"retweet_count":0,"reply_count":0,"like_count":0,"quote_count":0},"possibly_sensitive":false,"author_id":"927931548002811911","source":"Racing UK Results","geo":{},"attachments":{"media_keys":{}},"id":"964156458437931008","referenced_tweets":{}},{"entities":{"urls":{},"annotations":{},"mentions":[{"start":0,"end":14,"username":"pigeon_island","id":"218236795"},{"start":15,"end":28,"username":"FontwellPark","id":"237201160"}],"hashtags":{}},"text":"@pigeon_island @FontwellPark Bramble Brook\nTheos Charm\nLeith Hill Legasi\nGores Island","conversation_id":"954980016739241984","lang":"en","created_at":"2018-01-21T11:32:11.000Z","public_metrics":{"retweet_count":0,"reply_count":0,"like_count":0,"quote_count":0},"possibly_sensitive":false,"author_id":"20685802","source":"Twitter for Android","geo":{},"attachments":{"media_keys":{}},"id":"955040324837150720","in_reply_to_user_id":"218236795","referenced_tweets":[{"type":"replied_to","id":"954980016739241984"}]},{"entities":{"urls":{},"annotations":{},"mentions":[{"start":0,"end":14,"username":"pigeon_island","id":"218236795"},{"start":15,"end":28,"username":"FontwellPark","id":"237201160"}],"hashtags":[{"start":100,"end":113,"tag":"PigeonSwoop4"}]},"text":"@pigeon_island @FontwellPark 140- Bramble Brook, 210-Theo’s Charm,240-It’s a Steal,340-Gores Island #PigeonSwoop4","conversation_id":"954980016739241984","lang":"en","created_at":"2018-01-21T10:45:51.000Z","public_metrics":{"retweet_count":0,"reply_count":0,"like_count":0,"quote_count":0},"possibly_sensitive":false,"author_id":"36220474","source":"Twitter for iPhone","geo":{},"attachments":{"media_keys":{}},"id":"955028663443091456","in_reply_to_user_id":"218236795","referenced_tweets":[{"type":"replied_to","id":"954980016739241984"}]},{"entities":{"urls":{},"annotations":{},"mentions":[{"start":0,"end":14,"username":"pigeon_island","id":"218236795"}],"hashtags":[{"start":71,"end":84,"tag":"Pigeonswoop4"}]},"text":"@pigeon_island \nBramble brook\nChris pea green \nGoring one\nGores island\n#Pigeonswoop4","conversation_id":"955026962564763648","lang":"en","created_at":"2018-01-21T10:39:06.000Z","public_metrics":{"retweet_count":0,"reply_count":0,"like_count":0,"quote_count":0},"possibly_sensitive":false,"author_id":"620348164","source":"Twitter for iPhone","geo":{},"attachments":{"media_keys":{}},"id":"955026962564763648","in_reply_to_user_id":"218236795","referenced_tweets":{}},{"entities":{"urls":{},"annotations":{},"mentions":[{"start":0,"end":14,"username":"pigeon_island","id":"218236795"}],"hashtags":[{"start":101,"end":109,"tag":"PSwoop4"}]},"text":"@pigeon_island Fontwell 13.40 Bramble Brook 14.10 I See You Well 14.40 Goring One 15.40 Gores Island #PSwoop4 Cheers","conversation_id":"954971657445179393","lang":"en","created_at":"2018-01-21T06:59:20.000Z","public_metrics":{"retweet_count":0,"reply_count":0,"like_count":0,"quote_count":0},"possibly_sensitive":false,"author_id":"244570567","source":"Twitter for Android","geo":{},"attachments":{"media_keys":{}},"id":"954971657445179393","in_reply_to_user_id":"218236795","referenced_tweets":{}},{"entities":{"urls":{},"annotations":[{"start":28,"end":97,"probability":0.2642,"type":"Product","normalized_text":"140 Bramble Brook 210 Fourth Act 240 Colmers Hill 340 Gores Island"}],"mentions":[{"start":0,"end":14,"username":"pigeon_island","id":"218236795"}],"hashtags":[{"start":15,"end":28,"tag":"PigeonSwoop4"}]},"text":"@pigeon_island #PigeonSwoop4\n140 Bramble Brook \n210 Fourth Act \n240 Colmers Hill \n340 Gores Island","conversation_id":"954885153788133378","lang":"en","created_at":"2018-01-21T01:15:36.000Z","public_metrics":{"retweet_count":0,"reply_count":0,"like_count":0,"quote_count":0},"possibly_sensitive":false,"author_id":"295223277","source":"Twitter for Android","geo":{},"attachments":{"media_keys":{}},"id":"954885153788133378","in_reply_to_user_id":"218236795","referenced_tweets":{}},{"entities":{"urls":{},"annotations":[{"start":29,"end":78,"probability":0.4268,"type":"Product","normalized_text":"Bramble Brook Theo's Charm Goring One Gores Island"}],"mentions":[{"start":0,"end":14,"username":"pigeon_island","id":"218236795"},{"start":15,"end":28,"username":"FontwellPark","id":"237201160"}],"hashtags":{}},"text":"@pigeon_island @FontwellPark Bramble Brook\nTheo's Charm\nGoring One\nGores Island","conversation_id":"954780836590735360","lang":"en","created_at":"2018-01-20T18:35:07.000Z","public_metrics":{"retweet_count":0,"reply_count":0,"like_count":0,"quote_count":0},"possibly_sensitive":false,"author_id":"116834306","source":"Twitter for iPad","geo":{},"attachments":{"media_keys":{}},"id":"954784371462098944","in_reply_to_user_id":"218236795","referenced_tweets":[{"type":"replied_to","id":"954780836590735360"}]},{"entities":{"urls":{},"annotations":{},"mentions":{},"hashtags":{}},"text":"Al gores book tanks while brook refuting his book soars. Americans ain't stupid Al!","conversation_id":"905328072764911616","lang":"en","created_at":"2017-09-06T07:13:27.000Z","public_metrics":{"retweet_count":1,"reply_count":0,"like_count":0,"quote_count":0},"possibly_sensitive":false,"author_id":"824922594545635328","source":"Twitter for iPhone","geo":{},"attachments":{"media_keys":{}},"id":"905328072764911616","referenced_tweets":{}},{"entities":{"urls":[{"start":0,"end":23,"url":"https://t.co/dysHz442CZ","expanded_url":"http://trib.al/V82RFeL","display_url":"trib.al/V82RFeL"}],"annotations":[{"start":40,"end":44,"probability":0.5225,"type":"Person","normalized_text":"Gores"},{"start":61,"end":66,"probability":0.3974,"type":"Place","normalized_text":"Palace"},{"start":89,"end":94,"probability":0.6496,"type":"Organization","normalized_text":"Palace"},{"start":97,"end":103,"probability":0.7318,"type":"Organization","normalized_text":"Pistons"},{"start":106,"end":108,"probability":0.3774,"type":"Organization","normalized_text":"DTE"},{"start":111,"end":122,"probability":0.5665,"type":"Place","normalized_text":"Meadow Brook"}],"mentions":[{"start":27,"end":39,"username":"Bill_Shea19","id":"248999264"}],"hashtags":{}},"text":"https://t.co/dysHz442CZ MT @Bill_Shea19 Gores sought to sell Palace for $384M. He bought Palace, Pistons, DTE, Meadow Brook for $325M in '11","conversation_id":"790670166761832448","lang":"en","created_at":"2016-10-24T21:43:52.000Z","public_metrics":{"retweet_count":2,"reply_count":0,"like_count":1,"quote_count":1},"possibly_sensitive":false,"author_id":"29209404","source":"SocialFlow","geo":{},"attachments":{"media_keys":{}},"id":"790670166761832448","referenced_tweets":{}},{"entities":{"urls":{},"annotations":[{"start":17,"end":25,"probability":0.9959,"type":"Person","normalized_text":"Tom Gores"},{"start":42,"end":47,"probability":0.5152,"type":"Organization","normalized_text":"Palace"},{"start":70,"end":75,"probability":0.7362,"type":"Organization","normalized_text":"Palace"},{"start":78,"end":84,"probability":0.8318,"type":"Organization","normalized_text":"Pistons"},{"start":87,"end":89,"probability":0.5402,"type":"Organization","normalized_text":"DTE"},{"start":92,"end":103,"probability":0.4916,"type":"Organization","normalized_text":"Meadow Brook"}],"mentions":{},"hashtags":{}},"text":"Interesting that Tom Gores sought to sell Palace for $384M. He bought Palace, Pistons, DTE, Meadow Brook all for $325M in 2011.","conversation_id":"790663463521685504","lang":"en","created_at":"2016-10-24T21:17:14.000Z","public_metrics":{"retweet_count":5,"reply_count":2,"like_count":0,"quote_count":1},"possibly_sensitive":false,"author_id":"248999264","source":"Twitter Web Client","geo":{},"attachments":{"media_keys":{}},"id":"790663463521685504","referenced_tweets":{}}]
